{
    "geometry": [
      {
        "vertices": [
          [0.5, 0.5, 0.5],
          [-0.5, -0.5, 0.5],
          [0.5, -0.5, -0.5]
        ],
        "color": [255, 0, 0]
      },
      {
        "vertices": [
          [0.5, 0.5, 0.5],
          [0.5, -0.5, -0.5],
          [-0.5, 0.5, -0.5]
        ],
        "color": [0, 255, 0]
      },
      {
        "vertices": [
          [0.5, 0.5, 0.5],
          [-0.5, 0.5, -0.5],
          [-0.5, -0.5, 0.5]
        ],
        "color": [0, 0, 255]
      },
      {
        "vertices": [
          [-0.5, -0.5, 0.5],
          [-0.5, 0.5, -0.5],
          [0.5, -0.5, -0.5]
        ],
        "color": [255, 255, 0]
      }
    ]
  }